library/features/__init__.py
library/features/complex_feature/__init__.py
library/features/complex_feature/features_complex_feature.py
library/features/doctor_feature/__init__.py
library/features/doctor_feature/practitioner/__init__.py
library/features/doctor_feature/practitioner/v1/__init__.py
library/features/doctor_feature/practitioner/v1/mapping.py
library/features/doctor_feature/practitioner/v1/mapping_importer.py
library/features/doctor_feature/practitioner/v1/test/__init__.py
library/features/doctor_feature/practitioner/v1/test/test_doctor_feature_practitioner.py
library/features/doctor_feature/practitioner/v1/test/fhir_calls/__init__.py
library/features/doctor_feature/practitioner/v1/test/input/__init__.py
library/features/doctor_feature/practitioner_fail_on_data/__init__.py
library/features/doctor_feature/practitioner_fail_on_data/v1/__init__.py
library/features/doctor_feature/practitioner_fail_on_data/v1/features_doctor_feature_practitioner_fail_on_data_v1.py
library/features/doctor_feature/practitioner_fail_on_data/v1/mapping.py
library/features/doctor_feature/practitioner_fail_on_fhir_validation/__init__.py
library/features/doctor_feature/practitioner_fail_on_fhir_validation/v1/__init__.py
library/features/doctor_feature/practitioner_fail_on_fhir_validation/v1/features_doctor_feature_practitioner_fail_on_fhir_validation_v1.py
library/features/doctor_feature/practitioner_fail_on_fhir_validation/v1/mapping.py
library/features/doctor_feature/practitioner_fail_on_schema/__init__.py
library/features/doctor_feature/practitioner_fail_on_schema/v1/__init__.py
library/features/doctor_feature/practitioner_fail_on_schema/v1/features_doctor_feature_practitioner_fail_on_schema_v1.py
library/features/doctor_feature/practitioner_fail_on_schema/v1/mapping.py
library/features/doctor_feature/practitioner_inline/__init__.py
library/features/doctor_feature/practitioner_inline/v1/__init__.py
sparkpipelineframework_testing-4.0.5.dist-info/licenses/LICENSE
sparkpipelineframework_testing-4.0.5.dist-info/METADATA
sparkpipelineframework_testing-4.0.5.dist-info/WHEEL
sparkpipelineframework_testing-4.0.5.dist-info/top_level.txt
sparkpipelineframework_testing-4.0.5.dist-info/RECORD
