Metadata-Version: 2.4
Name: sparkpipelineframework.testing
Version: 4.0.5
Summary: Testing Framework for SparkPipelineFramework
Home-page: https://github.com/imranq2/SparkPipelineFramework.Testing
Author: Imran Qureshi
Author-email: imranq2@hotmail.com
Classifier: Development Status :: 4 - Beta
Classifier: Programming Language :: Python :: 3
Classifier: License :: OSI Approved :: Apache Software License
Classifier: Operating System :: OS Independent
Requires-Python: >=3.10
License-File: LICENSE
Requires-Dist: protobuf>=3
Requires-Dist: pyspark==3.5.1
Requires-Dist: pyarrow>=17.0.0
Requires-Dist: delta-spark==3.2.0
Requires-Dist: deprecated>=1.2.13
Requires-Dist: helix.fhir.client.sdk>=4.1.0
Requires-Dist: helix-mockserver-client>=2.0.4
Requires-Dist: sparkdataframecomparer>=2.0.13
Dynamic: author
Dynamic: author-email
Dynamic: classifier
Dynamic: description
Dynamic: description-content-type
Dynamic: home-page
Dynamic: license-file
Dynamic: requires-dist
Dynamic: requires-python
Dynamic: summary
